Python_Test_Migration/__init__.py
Python_Test_Migration/persistence/__init__.py
Python_Test_Migration/persistence/make_dill.py
Python_Test_Migration/persistence/un_dill.py
Python_Test_Migration/provider/__init__.py
Python_Test_Migration/provider/constant.py
Python_Test_Migration/provider/python_test_migration.py
Python_Test_Migration/service/__init__.py
Python_Test_Migration/service/app.py
Python_Test_Migration/service/app_service.py
Python_Test_Migration/test/__init__.py
Python_Test_Migration/test/Provider/__init__.py
Python_Test_Migration/test/Provider/test_python_test_migration.py
Python_Test_Migration/test/service/__init__.py
Python_Test_Migration/test/service/test_app_service.py
Python_Test_Migration/tier_one/__init__.py
Python_Test_Migration/tier_one/tier_one.py
Python_Test_Migration_Challenge-1.0.2.dist-info/LICENSE
Python_Test_Migration_Challenge-1.0.2.dist-info/METADATA
Python_Test_Migration_Challenge-1.0.2.dist-info/WHEEL
Python_Test_Migration_Challenge-1.0.2.dist-info/top_level.txt
Python_Test_Migration_Challenge-1.0.2.dist-info/RECORD
