Metadata-Version: 2.1
Name: Python-Test-Migration-Challenge
Version: 1.0.2
Summary: A Python package to do cloud migration Coding challenge
Home-page: https://github.com/alhadbhadekar/python-test-migrate-challenge
Author: Alhad Bhadekar
Author-email: alhad.bhadekar@gmail.com
License: MIT
Platform: UNKNOWN
Classifier: License :: OSI Approved :: MIT License
Classifier: Programming Language :: Python :: 3
Classifier: Programming Language :: Python :: 3.7
Requires-Dist: dill
